numpyneuron/__init__.py
numpyneuron/activation.py
numpyneuron/loss.py
numpyneuron/nn.py
numpyneuron-0.6.dist-info/METADATA
numpyneuron-0.6.dist-info/WHEEL
numpyneuron-0.6.dist-info/top_level.txt
numpyneuron-0.6.dist-info/RECORD
