Metadata-Version: 2.1
Name: numpyneuron
Version: 0.6
Summary: Simple, lightweight neural network framework built in numpy
Home-page: https://github.com/Jensen-holm/Numpy-Neuron
Author: Jensen Holm
Author-email: jensen.dev.01@gmail.com
Project-URL: Bug Tracker, https://github.com/Jensen-holm/Numpy-Neuron/issues
Requires-Python: >=3.6
Requires-Dist: numpy
Requires-Dist: gradio
Requires-Dist: tqdm
